ltadatamallcrawler/__init__.py
ltadatamallcrawler/_version.py
ltadatamallcrawler/cli.py
ltadatamallcrawler/config.py
ltadatamallcrawler/requestor.py
ltadatamallcrawler/settings.yaml
ltadatamallcrawler/urls.csv
ltadatamallcrawler-0.2.1.dist-info/DESCRIPTION.rst
ltadatamallcrawler-0.2.1.dist-info/METADATA
ltadatamallcrawler-0.2.1.dist-info/RECORD
ltadatamallcrawler-0.2.1.dist-info/WHEEL
ltadatamallcrawler-0.2.1.dist-info/entry_points.txt
ltadatamallcrawler-0.2.1.dist-info/metadata.json
ltadatamallcrawler-0.2.1.dist-info/top_level.txt
