Metadata-Version: 2.0
Name: ltadatamallcrawler
Version: 0.2.1
Summary: A package that gets traffic data from LTA datamall APIs.
Home-page: https://github.com/hiimivantang/ltadatamallcrawler
Author: Ivan Tang
Author-email: hiimivantang@gmail.com
License: GPL
Platform: UNKNOWN
Classifier: Development Status :: 2 - Pre-Alpha
Classifier: Intended Audience :: Developers
Classifier: License :: OSI Approved :: GNU General Public License (GPL)
Classifier: Natural Language :: English
Classifier: Operating System :: POSIX :: Linux
Classifier: Operating System :: MacOS :: MacOS X
Classifier: Programming Language :: Python :: 2
Classifier: Programming Language :: Python :: 2.7
Classifier: Programming Language :: Python :: 3
Classifier: Programming Language :: Python :: 3.3
Classifier: Programming Language :: Python :: 3.4
Classifier: Programming Language :: Python :: 3.5
Requires-Dist: requests
